askpablos_api/__init__.py
askpablos_api/auth.py
askpablos_api/config.py
askpablos_api/core.py
askpablos_api/exceptions.py
askpablos_api/http.py
askpablos_api/models.py
askpablos_api/utils.py
askpablos_api/validators.py
askpablos_api-0.2.0.dist-info/licenses/LICENSE
askpablos_api-0.2.0.dist-info/METADATA
askpablos_api-0.2.0.dist-info/WHEEL
askpablos_api-0.2.0.dist-info/top_level.txt
askpablos_api-0.2.0.dist-info/RECORD
