Metadata-Version: 2.4
Name: askpablos-api
Version: 0.2.0
Summary: Professional Python client for the AskPablos proxy API service
Author-email: Fawad Ali <fawadstar6@gmail.com>
Maintainer-email: Fawad Ali <fawadstar6@gmail.com>
License: MIT
Project-URL: Homepage, https://github.com/fawadss1/askpablos_api
Project-URL: Documentation, https://askpablos-api.readthedocs.io/en/latest/
Project-URL: Repository, https://github.com/fawadss1/askpablos_api
Project-URL: Issues, https://github.com/fawadss1/askpablos_api/issues
Project-URL: PyPI, https://pypi.org/project/askpablos-api/
Keywords: proxy,api,web-scraping,browser,http-client,askpablos
Classifier: Development Status :: 4 - Beta
Classifier: Intended Audience :: Developers
Classifier: License :: OSI Approved :: MIT License
Classifier: Natural Language :: English
Classifier: Operating System :: OS Independent
Classifier: Programming Language :: Python :: 3
Classifier: Programming Language :: Python :: 3.9
Classifier: Programming Language :: Python :: 3.10
Classifier: Programming Language :: Python :: 3.11
Classifier: Programming Language :: Python :: 3.12
Classifier: Programming Language :: Python :: 3.13
Classifier: Topic :: Internet :: WWW/HTTP :: Browsers
Classifier: Topic :: Internet :: Proxy Servers
Classifier: Topic :: Software Development :: Libraries :: Python Modules
Classifier: Topic :: System :: Networking
Requires-Python: >=3.9
License-File: LICENSE
Requires-Dist: requests>=2.25.0
Provides-Extra: dev
Requires-Dist: pytest>=6.0; extra == "dev"
Requires-Dist: pytest-cov>=2.0; extra == "dev"
Requires-Dist: black>=21.0; extra == "dev"
Requires-Dist: flake8>=3.8; extra == "dev"
Requires-Dist: mypy>=0.900; extra == "dev"
Requires-Dist: pre-commit>=2.0; extra == "dev"
Provides-Extra: docs
Requires-Dist: sphinx>=4.0; extra == "docs"
Requires-Dist: sphinx-rtd-theme>=1.0; extra == "docs"
Requires-Dist: myst-parser>=0.15; extra == "docs"
Dynamic: license-file
